nlxcaptcha/__init__.py
nlxcaptcha/nlxcaptcha.py
nlxcaptcha-2.0.dist-info/LICENSE
nlxcaptcha-2.0.dist-info/METADATA
nlxcaptcha-2.0.dist-info/WHEEL
nlxcaptcha-2.0.dist-info/top_level.txt
nlxcaptcha-2.0.dist-info/RECORD
